[
  {
    "protocol_version": "openreality.protocol.v0.1",
    "asset_id": "generic-agv-mobile-robot",
    "device_type": "mobile_robot",
    "manifest": {
      "protocol_version": "openreality.protocol.v0.1",
      "manifest_version": "device-manifest.v1",
      "asset_id": "generic-agv-mobile-robot",
      "profile_id": "generic-agv-mobile-robot",
      "device_id": "asset-generic-agv-mobile-robot",
      "device_type": "mobile_robot",
      "display_name": "Generic AGV Mobile Robot",
      "manufacturer": "RealityWarden",
      "model": "Generic AGV Mobile Robot",
      "category": "mobile-robotics",
      "simulator_fidelity": "semantic",
      "risk_class": "medium",
      "supported_adapters": [
        "simulator"
      ],
      "public_alpha_runnable": false
    },
    "component_graph": {
      "graph_version": "component-graph.v1",
      "device_type": "mobile_robot",
      "nodes": [
        {
          "id": "device",
          "type": "device",
          "label": "mobile_robot",
          "position": [
            0,
            0,
            0
          ]
        },
        {
          "id": "workspace",
          "type": "workspace",
          "label": "workspace",
          "metadata": {
            "x_min": -1.8,
            "x_max": 1.8,
            "y_min": 0,
            "z_min": -1.4,
            "z_max": 1.4,
            "y_max": 1.8
          }
        },
        {
          "id": "safe_zone",
          "type": "zone",
          "label": "safe_zone",
          "position": [
            0.75,
            0.13,
            0.2
          ],
          "metadata": {
            "size": [
              0.55,
              0.55
            ]
          }
        },
        {
          "id": "inspection_zone",
          "type": "zone",
          "label": "inspection_zone",
          "position": [
            -0.55,
            0.13,
            0.2
          ],
          "metadata": {
            "size": [
              0.55,
              0.55
            ]
          }
        },
        {
          "id": "restricted_zone",
          "type": "zone",
          "label": "restricted_zone",
          "position": [
            0.05,
            0.13,
            0.55
          ],
          "metadata": {
            "size": [
              0.45,
              0.45
            ]
          }
        },
        {
          "id": "unsafe_zone",
          "type": "zone",
          "label": "unsafe_zone",
          "position": [
            -0.9,
            0.13,
            -0.55
          ],
          "metadata": {
            "size": [
              0.45,
              0.45
            ]
          }
        },
        {
          "id": "red_cube",
          "type": "object",
          "label": "red_cube",
          "position": [
            -0.55,
            0.18,
            0.2
          ],
          "metadata": {
            "position": [
              -0.55,
              0.18,
              0.2
            ],
            "size": 0.2
          }
        },
        {
          "id": "blue_cube",
          "type": "object",
          "label": "blue_cube",
          "position": [
            0.45,
            0.18,
            -0.25
          ],
          "metadata": {
            "position": [
              0.45,
              0.18,
              -0.25
            ],
            "size": 0.2
          }
        },
        {
          "id": "glass_cup",
          "type": "object",
          "label": "glass_cup",
          "position": [
            0.05,
            0.2,
            0.55
          ],
          "metadata": {
            "position": [
              0.05,
              0.2,
              0.55
            ],
            "radius": 0.09,
            "height": 0.28
          }
        },
        {
          "id": "indicator:safe",
          "type": "indicator",
          "label": "safe",
          "metadata": {
            "value": "safe_zone"
          }
        },
        {
          "id": "indicator:unsafe",
          "type": "indicator",
          "label": "unsafe",
          "metadata": {
            "value": "restricted_zone"
          }
        }
      ],
      "edges": [
        {
          "from": "workspace",
          "to": "device",
          "relation": "contains"
        },
        {
          "from": "workspace",
          "to": "safe_zone",
          "relation": "contains"
        },
        {
          "from": "device",
          "to": "safe_zone",
          "relation": "targets"
        },
        {
          "from": "workspace",
          "to": "inspection_zone",
          "relation": "contains"
        },
        {
          "from": "device",
          "to": "inspection_zone",
          "relation": "targets"
        },
        {
          "from": "workspace",
          "to": "restricted_zone",
          "relation": "contains"
        },
        {
          "from": "device",
          "to": "restricted_zone",
          "relation": "targets"
        },
        {
          "from": "workspace",
          "to": "unsafe_zone",
          "relation": "contains"
        },
        {
          "from": "device",
          "to": "unsafe_zone",
          "relation": "targets"
        },
        {
          "from": "workspace",
          "to": "red_cube",
          "relation": "contains"
        },
        {
          "from": "device",
          "to": "red_cube",
          "relation": "targets"
        },
        {
          "from": "workspace",
          "to": "blue_cube",
          "relation": "contains"
        },
        {
          "from": "device",
          "to": "blue_cube",
          "relation": "targets"
        },
        {
          "from": "workspace",
          "to": "glass_cup",
          "relation": "contains"
        },
        {
          "from": "device",
          "to": "glass_cup",
          "relation": "targets"
        },
        {
          "from": "device",
          "to": "indicator:safe",
          "relation": "monitors"
        },
        {
          "from": "device",
          "to": "indicator:unsafe",
          "relation": "monitors"
        }
      ]
    },
    "normalized_capabilities": [
      {
        "raw": "navigate_to",
        "normalized": "motion.navigate_to",
        "capability_class": "motion",
        "device_types": [
          "mobile_robot"
        ],
        "requires_target": true,
        "requires_value": false,
        "risk_hint": "medium"
      },
      {
        "raw": "scan_area",
        "normalized": "vision.scan_area",
        "capability_class": "vision",
        "device_types": [
          "robot_arm",
          "camera_sensor"
        ],
        "requires_target": false,
        "requires_value": false,
        "risk_hint": "low"
      },
      {
        "raw": "dock",
        "normalized": "motion.dock",
        "capability_class": "motion",
        "device_types": [
          "mobile_robot"
        ],
        "requires_target": true,
        "requires_value": false,
        "risk_hint": "low"
      }
    ],
    "safety_profile": {
      "profile_version": "safety-profile.v1",
      "risk_class": "medium",
      "forbidden_zones": [
        "restricted_zone",
        "unsafe_zone"
      ],
      "workspace": {
        "x_min": -1.8,
        "x_max": 1.8,
        "y_min": 0,
        "z_min": -1.4,
        "z_max": 1.4,
        "y_max": 1.8
      },
      "max_speed": "normal",
      "force_limit": "medium",
      "policies": {
        "allow_throwing": false,
        "allow_high_force": false,
        "allow_outside_workspace": false,
        "require_logging": true,
        "require_human_confirmation_for_risky_actions": true
      }
    },
    "runtime_permissions": [
      {
        "permission": "simulation.run",
        "allowed": false,
        "scope": "mobile_robot"
      },
      {
        "permission": "audit.export",
        "allowed": true,
        "scope": "mobile_robot"
      },
      {
        "permission": "real_device.connect",
        "allowed": false,
        "scope": "mobile_robot"
      },
      {
        "permission": "real_device.execute",
        "allowed": false,
        "scope": "mobile_robot"
      }
    ],
    "adapter_binding": {
      "binding_version": "adapter-binding.v1",
      "adapter_id": "simulator-generic-agv-mobile-robot",
      "adapter_type": "simulator",
      "interface": "AdapterInterface",
      "transport": "virtual-device-runtime",
      "supported_commands": [
        "navigate_to",
        "scan_area",
        "dock"
      ],
      "real_device_enabled": false
    },
    "source_asset": {
      "license": "project-owned-generic",
      "brand": "generic",
      "source": "created-for-open-reality-studio",
      "allowed_use": [
        "simulation",
        "development",
        "testing"
      ]
    }
  },
  {
    "protocol_version": "openreality.protocol.v0.1",
    "asset_id": "generic-conveyor-belt",
    "device_type": "conveyor_belt",
    "manifest": {
      "protocol_version": "openreality.protocol.v0.1",
      "manifest_version": "device-manifest.v1",
      "asset_id": "generic-conveyor-belt",
      "profile_id": "generic-conveyor-belt",
      "device_id": "asset-generic-conveyor-belt",
      "device_type": "conveyor_belt",
      "display_name": "Generic Conveyor Belt",
      "manufacturer": "RealityWarden",
      "model": "Generic Conveyor Belt",
      "category": "material-handling",
      "simulator_fidelity": "semantic",
      "risk_class": "medium",
      "supported_adapters": [
        "simulator"
      ],
      "public_alpha_runnable": false
    },
    "component_graph": {
      "graph_version": "component-graph.v1",
      "device_type": "conveyor_belt",
      "nodes": [
        {
          "id": "device",
          "type": "device",
          "label": "conveyor_belt",
          "position": [
            0,
            0,
            0
          ]
        },
        {
          "id": "workspace",
          "type": "workspace",
          "label": "workspace",
          "metadata": {
            "x_min": -1.8,
            "x_max": 1.8,
            "y_min": 0,
            "z_min": -1.4,
            "z_max": 1.4,
            "y_max": 1.8
          }
        },
        {
          "id": "safe_zone",
          "type": "zone",
          "label": "safe_zone",
          "position": [
            0.75,
            0.13,
            0.2
          ],
          "metadata": {
            "size": [
              0.55,
              0.55
            ]
          }
        },
        {
          "id": "inspection_zone",
          "type": "zone",
          "label": "inspection_zone",
          "position": [
            -0.55,
            0.13,
            0.2
          ],
          "metadata": {
            "size": [
              0.55,
              0.55
            ]
          }
        },
        {
          "id": "restricted_zone",
          "type": "zone",
          "label": "restricted_zone",
          "position": [
            0.05,
            0.13,
            0.55
          ],
          "metadata": {
            "size": [
              0.45,
              0.45
            ]
          }
        },
        {
          "id": "unsafe_zone",
          "type": "zone",
          "label": "unsafe_zone",
          "position": [
            -0.9,
            0.13,
            -0.55
          ],
          "metadata": {
            "size": [
              0.45,
              0.45
            ]
          }
        },
        {
          "id": "red_cube",
          "type": "object",
          "label": "red_cube",
          "position": [
            -0.55,
            0.18,
            0.2
          ],
          "metadata": {
            "position": [
              -0.55,
              0.18,
              0.2
            ],
            "size": 0.2
          }
        },
        {
          "id": "blue_cube",
          "type": "object",
          "label": "blue_cube",
          "position": [
            0.45,
            0.18,
            -0.25
          ],
          "metadata": {
            "position": [
              0.45,
              0.18,
              -0.25
            ],
            "size": 0.2
          }
        },
        {
          "id": "glass_cup",
          "type": "object",
          "label": "glass_cup",
          "position": [
            0.05,
            0.2,
            0.55
          ],
          "metadata": {
            "position": [
              0.05,
              0.2,
              0.55
            ],
            "radius": 0.09,
            "height": 0.28
          }
        },
        {
          "id": "indicator:safe",
          "type": "indicator",
          "label": "safe",
          "metadata": {
            "value": "safe_zone"
          }
        },
        {
          "id": "indicator:unsafe",
          "type": "indicator",
          "label": "unsafe",
          "metadata": {
            "value": "restricted_zone"
          }
        }
      ],
      "edges": [
        {
          "from": "workspace",
          "to": "device",
          "relation": "contains"
        },
        {
          "from": "workspace",
          "to": "safe_zone",
          "relation": "contains"
        },
        {
          "from": "device",
          "to": "safe_zone",
          "relation": "targets"
        },
        {
          "from": "workspace",
          "to": "inspection_zone",
          "relation": "contains"
        },
        {
          "from": "device",
          "to": "inspection_zone",
          "relation": "targets"
        },
        {
          "from": "workspace",
          "to": "restricted_zone",
          "relation": "contains"
        },
        {
          "from": "device",
          "to": "restricted_zone",
          "relation": "targets"
        },
        {
          "from": "workspace",
          "to": "unsafe_zone",
          "relation": "contains"
        },
        {
          "from": "device",
          "to": "unsafe_zone",
          "relation": "targets"
        },
        {
          "from": "workspace",
          "to": "red_cube",
          "relation": "contains"
        },
        {
          "from": "device",
          "to": "red_cube",
          "relation": "targets"
        },
        {
          "from": "workspace",
          "to": "blue_cube",
          "relation": "contains"
        },
        {
          "from": "device",
          "to": "blue_cube",
          "relation": "targets"
        },
        {
          "from": "workspace",
          "to": "glass_cup",
          "relation": "contains"
        },
        {
          "from": "device",
          "to": "glass_cup",
          "relation": "targets"
        },
        {
          "from": "device",
          "to": "indicator:safe",
          "relation": "monitors"
        },
        {
          "from": "device",
          "to": "indicator:unsafe",
          "relation": "monitors"
        }
      ]
    },
    "normalized_capabilities": [
      {
        "raw": "start_belt",
        "normalized": "motion.start_belt",
        "capability_class": "motion",
        "device_types": [
          "conveyor_belt"
        ],
        "requires_target": false,
        "requires_value": false,
        "risk_hint": "medium"
      },
      {
        "raw": "sort_item",
        "normalized": "motion.sort_item",
        "capability_class": "motion",
        "device_types": [
          "conveyor_belt"
        ],
        "requires_target": true,
        "requires_value": false,
        "risk_hint": "medium"
      },
      {
        "raw": "stop_belt",
        "normalized": "motion.stop_belt",
        "capability_class": "motion",
        "device_types": [
          "conveyor_belt"
        ],
        "requires_target": false,
        "requires_value": false,
        "risk_hint": "low"
      }
    ],
    "safety_profile": {
      "profile_version": "safety-profile.v1",
      "risk_class": "medium",
      "forbidden_zones": [
        "restricted_zone",
        "unsafe_zone"
      ],
      "workspace": {
        "x_min": -1.8,
        "x_max": 1.8,
        "y_min": 0,
        "z_min": -1.4,
        "z_max": 1.4,
        "y_max": 1.8
      },
      "max_speed": "normal",
      "force_limit": "medium",
      "policies": {
        "allow_throwing": false,
        "allow_high_force": false,
        "allow_outside_workspace": false,
        "require_logging": true,
        "require_human_confirmation_for_risky_actions": true
      }
    },
    "runtime_permissions": [
      {
        "permission": "simulation.run",
        "allowed": false,
        "scope": "conveyor_belt"
      },
      {
        "permission": "audit.export",
        "allowed": true,
        "scope": "conveyor_belt"
      },
      {
        "permission": "real_device.connect",
        "allowed": false,
        "scope": "conveyor_belt"
      },
      {
        "permission": "real_device.execute",
        "allowed": false,
        "scope": "conveyor_belt"
      }
    ],
    "adapter_binding": {
      "binding_version": "adapter-binding.v1",
      "adapter_id": "simulator-generic-conveyor-belt",
      "adapter_type": "simulator",
      "interface": "AdapterInterface",
      "transport": "virtual-device-runtime",
      "supported_commands": [
        "start_belt",
        "sort_item",
        "stop_belt"
      ],
      "real_device_enabled": false
    },
    "source_asset": {
      "license": "project-owned-generic",
      "brand": "generic",
      "source": "created-for-open-reality-studio",
      "allowed_use": [
        "simulation",
        "development",
        "testing"
      ]
    }
  },
  {
    "protocol_version": "openreality.protocol.v0.1",
    "asset_id": "generic-industrial-robot-arm",
    "device_type": "robot_arm",
    "manifest": {
      "protocol_version": "openreality.protocol.v0.1",
      "manifest_version": "device-manifest.v1",
      "asset_id": "generic-industrial-robot-arm",
      "profile_id": "generic-industrial-robot-arm",
      "device_id": "asset-generic-industrial-robot-arm",
      "device_type": "robot_arm",
      "display_name": "Generic Industrial Robot Arm",
      "manufacturer": "RealityWarden",
      "model": "Generic Industrial Robot Arm",
      "category": "robotics",
      "simulator_fidelity": "semantic",
      "risk_class": "medium",
      "supported_adapters": [
        "simulator"
      ],
      "public_alpha_runnable": true
    },
    "component_graph": {
      "graph_version": "component-graph.v1",
      "device_type": "robot_arm",
      "nodes": [
        {
          "id": "device",
          "type": "device",
          "label": "robot_arm",
          "position": [
            0,
            0,
            0
          ]
        },
        {
          "id": "workspace",
          "type": "workspace",
          "label": "workspace",
          "metadata": {
            "x_min": -1.8,
            "x_max": 1.8,
            "y_min": 0,
            "z_min": -1.4,
            "z_max": 1.4,
            "y_max": 1.8
          }
        },
        {
          "id": "pickup_zone",
          "type": "zone",
          "label": "pickup_zone",
          "position": [
            -0.55,
            0.13,
            0.2
          ],
          "metadata": {
            "size": [
              0.55,
              0.55
            ]
          }
        },
        {
          "id": "right_safe_zone",
          "type": "zone",
          "label": "right_safe_zone",
          "position": [
            0.95,
            0.13,
            0.2
          ],
          "metadata": {
            "size": [
              0.55,
              0.55
            ]
          }
        },
        {
          "id": "front_safe_zone",
          "type": "zone",
          "label": "front_safe_zone",
          "position": [
            0,
            0.13,
            0.75
          ],
          "metadata": {
            "size": [
              0.55,
              0.55
            ]
          }
        },
        {
          "id": "back_safe_zone",
          "type": "zone",
          "label": "back_safe_zone",
          "position": [
            0,
            0.13,
            -0.75
          ],
          "metadata": {
            "size": [
              0.55,
              0.55
            ]
          }
        },
        {
          "id": "left_safe_zone",
          "type": "zone",
          "label": "left_safe_zone",
          "position": [
            -0.95,
            0.13,
            -0.3
          ],
          "metadata": {
            "size": [
              0.55,
              0.55
            ]
          }
        },
        {
          "id": "safe_zone",
          "type": "zone",
          "label": "safe_zone",
          "position": [
            0.75,
            0.13,
            0.2
          ],
          "metadata": {
            "size": [
              0.55,
              0.55
            ]
          }
        },
        {
          "id": "inspection_zone",
          "type": "zone",
          "label": "inspection_zone",
          "position": [
            -0.55,
            0.13,
            0.2
          ],
          "metadata": {
            "size": [
              0.55,
              0.55
            ]
          }
        },
        {
          "id": "restricted_zone",
          "type": "zone",
          "label": "restricted_zone",
          "position": [
            0.05,
            0.13,
            0.55
          ],
          "metadata": {
            "size": [
              0.45,
              0.45
            ]
          }
        },
        {
          "id": "unsafe_zone",
          "type": "zone",
          "label": "unsafe_zone",
          "position": [
            -0.9,
            0.13,
            -0.55
          ],
          "metadata": {
            "size": [
              0.45,
              0.45
            ]
          }
        },
        {
          "id": "red_cube",
          "type": "object",
          "label": "red_cube",
          "position": [
            -0.55,
            0.18,
            0.2
          ],
          "metadata": {
            "position": [
              -0.55,
              0.18,
              0.2
            ],
            "size": 0.2
          }
        },
        {
          "id": "blue_cube",
          "type": "object",
          "label": "blue_cube",
          "position": [
            0.45,
            0.18,
            -0.25
          ],
          "metadata": {
            "position": [
              0.45,
              0.18,
              -0.25
            ],
            "size": 0.2
          }
        },
        {
          "id": "glass_cup",
          "type": "object",
          "label": "glass_cup",
          "position": [
            0.05,
            0.2,
            0.55
          ],
          "metadata": {
            "position": [
              0.05,
              0.2,
              0.55
            ],
            "radius": 0.09,
            "height": 0.28
          }
        },
        {
          "id": "indicator:safe",
          "type": "indicator",
          "label": "safe",
          "metadata": {
            "value": "safe_zone"
          }
        },
        {
          "id": "indicator:unsafe",
          "type": "indicator",
          "label": "unsafe",
          "metadata": {
            "value": "restricted_zone"
          }
        }
      ],
      "edges": [
        {
          "from": "workspace",
          "to": "device",
          "relation": "contains"
        },
        {
          "from": "workspace",
          "to": "pickup_zone",
          "relation": "contains"
        },
        {
          "from": "device",
          "to": "pickup_zone",
          "relation": "targets"
        },
        {
          "from": "workspace",
          "to": "right_safe_zone",
          "relation": "contains"
        },
        {
          "from": "device",
          "to": "right_safe_zone",
          "relation": "targets"
        },
        {
          "from": "workspace",
          "to": "front_safe_zone",
          "relation": "contains"
        },
        {
          "from": "device",
          "to": "front_safe_zone",
          "relation": "targets"
        },
        {
          "from": "workspace",
          "to": "back_safe_zone",
          "relation": "contains"
        },
        {
          "from": "device",
          "to": "back_safe_zone",
          "relation": "targets"
        },
        {
          "from": "workspace",
          "to": "left_safe_zone",
          "relation": "contains"
        },
        {
          "from": "device",
          "to": "left_safe_zone",
          "relation": "targets"
        },
        {
          "from": "workspace",
          "to": "safe_zone",
          "relation": "contains"
        },
        {
          "from": "device",
          "to": "safe_zone",
          "relation": "targets"
        },
        {
          "from": "workspace",
          "to": "inspection_zone",
          "relation": "contains"
        },
        {
          "from": "device",
          "to": "inspection_zone",
          "relation": "targets"
        },
        {
          "from": "workspace",
          "to": "restricted_zone",
          "relation": "contains"
        },
        {
          "from": "device",
          "to": "restricted_zone",
          "relation": "targets"
        },
        {
          "from": "workspace",
          "to": "unsafe_zone",
          "relation": "contains"
        },
        {
          "from": "device",
          "to": "unsafe_zone",
          "relation": "targets"
        },
        {
          "from": "workspace",
          "to": "red_cube",
          "relation": "contains"
        },
        {
          "from": "device",
          "to": "red_cube",
          "relation": "targets"
        },
        {
          "from": "workspace",
          "to": "blue_cube",
          "relation": "contains"
        },
        {
          "from": "device",
          "to": "blue_cube",
          "relation": "targets"
        },
        {
          "from": "workspace",
          "to": "glass_cup",
          "relation": "contains"
        },
        {
          "from": "device",
          "to": "glass_cup",
          "relation": "targets"
        },
        {
          "from": "device",
          "to": "indicator:safe",
          "relation": "monitors"
        },
        {
          "from": "device",
          "to": "indicator:unsafe",
          "relation": "monitors"
        }
      ]
    },
    "normalized_capabilities": [
      {
        "raw": "scan_area",
        "normalized": "vision.scan_area",
        "capability_class": "vision",
        "device_types": [
          "robot_arm",
          "camera_sensor"
        ],
        "requires_target": false,
        "requires_value": false,
        "risk_hint": "low"
      },
      {
        "raw": "identify_object",
        "normalized": "manipulation.identify_object",
        "capability_class": "manipulation",
        "device_types": [
          "robot_arm"
        ],
        "requires_target": true,
        "requires_value": false,
        "risk_hint": "low"
      },
      {
        "raw": "move_to_pose",
        "normalized": "motion.move_to_pose",
        "capability_class": "motion",
        "device_types": [
          "robot_arm"
        ],
        "requires_target": true,
        "requires_value": false,
        "risk_hint": "medium"
      },
      {
        "raw": "grasp",
        "normalized": "manipulation.grasp",
        "capability_class": "manipulation",
        "device_types": [
          "robot_arm"
        ],
        "requires_target": true,
        "requires_value": false,
        "risk_hint": "medium"
      },
      {
        "raw": "release",
        "normalized": "manipulation.release",
        "capability_class": "manipulation",
        "device_types": [
          "robot_arm"
        ],
        "requires_target": true,
        "requires_value": false,
        "risk_hint": "medium"
      },
      {
        "raw": "return_home",
        "normalized": "motion.return_home",
        "capability_class": "motion",
        "device_types": [
          "robot_arm"
        ],
        "requires_target": false,
        "requires_value": false,
        "risk_hint": "low"
      }
    ],
    "safety_profile": {
      "profile_version": "safety-profile.v1",
      "risk_class": "medium",
      "forbidden_zones": [
        "restricted_zone",
        "unsafe_zone"
      ],
      "workspace": {
        "x_min": -1.8,
        "x_max": 1.8,
        "y_min": 0,
        "z_min": -1.4,
        "z_max": 1.4,
        "y_max": 1.8
      },
      "max_speed": "normal",
      "force_limit": "medium",
      "policies": {
        "allow_throwing": false,
        "allow_high_force": false,
        "allow_outside_workspace": false,
        "require_logging": true,
        "require_human_confirmation_for_risky_actions": true
      }
    },
    "runtime_permissions": [
      {
        "permission": "simulation.run",
        "allowed": true,
        "scope": "robot_arm"
      },
      {
        "permission": "audit.export",
        "allowed": true,
        "scope": "robot_arm"
      },
      {
        "permission": "real_device.connect",
        "allowed": false,
        "scope": "robot_arm"
      },
      {
        "permission": "real_device.execute",
        "allowed": false,
        "scope": "robot_arm"
      }
    ],
    "adapter_binding": {
      "binding_version": "adapter-binding.v1",
      "adapter_id": "simulator-generic-industrial-robot-arm",
      "adapter_type": "simulator",
      "interface": "AdapterInterface",
      "transport": "virtual-device-runtime",
      "supported_commands": [
        "scan_area",
        "identify_object",
        "move_to_pose",
        "grasp",
        "release",
        "return_home"
      ],
      "real_device_enabled": false
    },
    "source_asset": {
      "license": "project-owned-generic",
      "brand": "generic",
      "source": "created-for-open-reality-studio",
      "allowed_use": [
        "simulation",
        "development",
        "testing"
      ]
    }
  },
  {
    "protocol_version": "openreality.protocol.v0.1",
    "asset_id": "generic-lab-instrument",
    "device_type": "lab_instrument",
    "manifest": {
      "protocol_version": "openreality.protocol.v0.1",
      "manifest_version": "device-manifest.v1",
      "asset_id": "generic-lab-instrument",
      "profile_id": "generic-lab-instrument",
      "device_id": "asset-generic-lab-instrument",
      "device_type": "lab_instrument",
      "display_name": "Generic Lab Instrument",
      "manufacturer": "RealityWarden",
      "model": "Generic Lab Instrument",
      "category": "lab-equipment",
      "simulator_fidelity": "semantic",
      "risk_class": "medium",
      "supported_adapters": [
        "simulator"
      ],
      "public_alpha_runnable": false
    },
    "component_graph": {
      "graph_version": "component-graph.v1",
      "device_type": "lab_instrument",
      "nodes": [
        {
          "id": "device",
          "type": "device",
          "label": "lab_instrument",
          "position": [
            0,
            0,
            0
          ]
        },
        {
          "id": "workspace",
          "type": "workspace",
          "label": "workspace",
          "metadata": {
            "x_min": -1.8,
            "x_max": 1.8,
            "y_min": 0,
            "z_min": -1.4,
            "z_max": 1.4,
            "y_max": 1.8
          }
        },
        {
          "id": "safe_zone",
          "type": "zone",
          "label": "safe_zone",
          "position": [
            0.75,
            0.13,
            0.2
          ],
          "metadata": {
            "size": [
              0.55,
              0.55
            ]
          }
        },
        {
          "id": "inspection_zone",
          "type": "zone",
          "label": "inspection_zone",
          "position": [
            -0.55,
            0.13,
            0.2
          ],
          "metadata": {
            "size": [
              0.55,
              0.55
            ]
          }
        },
        {
          "id": "restricted_zone",
          "type": "zone",
          "label": "restricted_zone",
          "position": [
            0.05,
            0.13,
            0.55
          ],
          "metadata": {
            "size": [
              0.45,
              0.45
            ]
          }
        },
        {
          "id": "unsafe_zone",
          "type": "zone",
          "label": "unsafe_zone",
          "position": [
            -0.9,
            0.13,
            -0.55
          ],
          "metadata": {
            "size": [
              0.45,
              0.45
            ]
          }
        },
        {
          "id": "red_cube",
          "type": "object",
          "label": "red_cube",
          "position": [
            -0.55,
            0.18,
            0.2
          ],
          "metadata": {
            "position": [
              -0.55,
              0.18,
              0.2
            ],
            "size": 0.2
          }
        },
        {
          "id": "blue_cube",
          "type": "object",
          "label": "blue_cube",
          "position": [
            0.45,
            0.18,
            -0.25
          ],
          "metadata": {
            "position": [
              0.45,
              0.18,
              -0.25
            ],
            "size": 0.2
          }
        },
        {
          "id": "glass_cup",
          "type": "object",
          "label": "glass_cup",
          "position": [
            0.05,
            0.2,
            0.55
          ],
          "metadata": {
            "position": [
              0.05,
              0.2,
              0.55
            ],
            "radius": 0.09,
            "height": 0.28
          }
        },
        {
          "id": "indicator:safe",
          "type": "indicator",
          "label": "safe",
          "metadata": {
            "value": "safe_zone"
          }
        },
        {
          "id": "indicator:unsafe",
          "type": "indicator",
          "label": "unsafe",
          "metadata": {
            "value": "restricted_zone"
          }
        }
      ],
      "edges": [
        {
          "from": "workspace",
          "to": "device",
          "relation": "contains"
        },
        {
          "from": "workspace",
          "to": "safe_zone",
          "relation": "contains"
        },
        {
          "from": "device",
          "to": "safe_zone",
          "relation": "targets"
        },
        {
          "from": "workspace",
          "to": "inspection_zone",
          "relation": "contains"
        },
        {
          "from": "device",
          "to": "inspection_zone",
          "relation": "targets"
        },
        {
          "from": "workspace",
          "to": "restricted_zone",
          "relation": "contains"
        },
        {
          "from": "device",
          "to": "restricted_zone",
          "relation": "targets"
        },
        {
          "from": "workspace",
          "to": "unsafe_zone",
          "relation": "contains"
        },
        {
          "from": "device",
          "to": "unsafe_zone",
          "relation": "targets"
        },
        {
          "from": "workspace",
          "to": "red_cube",
          "relation": "contains"
        },
        {
          "from": "device",
          "to": "red_cube",
          "relation": "targets"
        },
        {
          "from": "workspace",
          "to": "blue_cube",
          "relation": "contains"
        },
        {
          "from": "device",
          "to": "blue_cube",
          "relation": "targets"
        },
        {
          "from": "workspace",
          "to": "glass_cup",
          "relation": "contains"
        },
        {
          "from": "device",
          "to": "glass_cup",
          "relation": "targets"
        },
        {
          "from": "device",
          "to": "indicator:safe",
          "relation": "monitors"
        },
        {
          "from": "device",
          "to": "indicator:unsafe",
          "relation": "monitors"
        }
      ]
    },
    "normalized_capabilities": [
      {
        "raw": "read_measurement",
        "normalized": "lab.read_measurement",
        "capability_class": "lab",
        "device_types": [
          "lab_instrument"
        ],
        "requires_target": false,
        "requires_value": false,
        "risk_hint": "low"
      },
      {
        "raw": "set_parameter",
        "normalized": "lab.set_parameter",
        "capability_class": "lab",
        "device_types": [
          "lab_instrument"
        ],
        "requires_target": true,
        "requires_value": true,
        "risk_hint": "medium"
      },
      {
        "raw": "start_test",
        "normalized": "lab.start_test",
        "capability_class": "lab",
        "device_types": [
          "lab_instrument"
        ],
        "requires_target": false,
        "requires_value": false,
        "risk_hint": "medium"
      },
      {
        "raw": "stop_test",
        "normalized": "lab.stop_test",
        "capability_class": "lab",
        "device_types": [
          "lab_instrument"
        ],
        "requires_target": false,
        "requires_value": false,
        "risk_hint": "low"
      }
    ],
    "safety_profile": {
      "profile_version": "safety-profile.v1",
      "risk_class": "medium",
      "forbidden_zones": [
        "restricted_zone",
        "unsafe_zone"
      ],
      "workspace": {
        "x_min": -1.8,
        "x_max": 1.8,
        "y_min": 0,
        "z_min": -1.4,
        "z_max": 1.4,
        "y_max": 1.8
      },
      "max_speed": "normal",
      "force_limit": "medium",
      "policies": {
        "allow_throwing": false,
        "allow_high_force": false,
        "allow_outside_workspace": false,
        "require_logging": true,
        "require_human_confirmation_for_risky_actions": true
      }
    },
    "runtime_permissions": [
      {
        "permission": "simulation.run",
        "allowed": false,
        "scope": "lab_instrument"
      },
      {
        "permission": "audit.export",
        "allowed": true,
        "scope": "lab_instrument"
      },
      {
        "permission": "real_device.connect",
        "allowed": false,
        "scope": "lab_instrument"
      },
      {
        "permission": "real_device.execute",
        "allowed": false,
        "scope": "lab_instrument"
      }
    ],
    "adapter_binding": {
      "binding_version": "adapter-binding.v1",
      "adapter_id": "simulator-generic-lab-instrument",
      "adapter_type": "simulator",
      "interface": "AdapterInterface",
      "transport": "virtual-device-runtime",
      "supported_commands": [
        "read_measurement",
        "set_parameter",
        "start_test",
        "stop_test"
      ],
      "real_device_enabled": false
    },
    "source_asset": {
      "license": "project-owned-generic",
      "brand": "generic",
      "source": "created-for-open-reality-studio",
      "allowed_use": [
        "simulation",
        "development",
        "testing"
      ]
    }
  },
  {
    "protocol_version": "openreality.protocol.v0.1",
    "asset_id": "generic-plc-cabinet",
    "device_type": "plc_cabinet",
    "manifest": {
      "protocol_version": "openreality.protocol.v0.1",
      "manifest_version": "device-manifest.v1",
      "asset_id": "generic-plc-cabinet",
      "profile_id": "generic-plc-cabinet",
      "device_id": "asset-generic-plc-cabinet",
      "device_type": "plc_cabinet",
      "display_name": "Generic PLC Cabinet",
      "manufacturer": "RealityWarden",
      "model": "Generic PLC Cabinet",
      "category": "controls",
      "simulator_fidelity": "semantic",
      "risk_class": "medium",
      "supported_adapters": [
        "simulator"
      ],
      "public_alpha_runnable": false
    },
    "component_graph": {
      "graph_version": "component-graph.v1",
      "device_type": "plc_cabinet",
      "nodes": [
        {
          "id": "device",
          "type": "device",
          "label": "plc_cabinet",
          "position": [
            0,
            0,
            0
          ]
        },
        {
          "id": "workspace",
          "type": "workspace",
          "label": "workspace",
          "metadata": {
            "x_min": -1.8,
            "x_max": 1.8,
            "y_min": 0,
            "z_min": -1.4,
            "z_max": 1.4,
            "y_max": 1.8
          }
        },
        {
          "id": "safe_zone",
          "type": "zone",
          "label": "safe_zone",
          "position": [
            0.75,
            0.13,
            0.2
          ],
          "metadata": {
            "size": [
              0.55,
              0.55
            ]
          }
        },
        {
          "id": "inspection_zone",
          "type": "zone",
          "label": "inspection_zone",
          "position": [
            -0.55,
            0.13,
            0.2
          ],
          "metadata": {
            "size": [
              0.55,
              0.55
            ]
          }
        },
        {
          "id": "restricted_zone",
          "type": "zone",
          "label": "restricted_zone",
          "position": [
            0.05,
            0.13,
            0.55
          ],
          "metadata": {
            "size": [
              0.45,
              0.45
            ]
          }
        },
        {
          "id": "unsafe_zone",
          "type": "zone",
          "label": "unsafe_zone",
          "position": [
            -0.9,
            0.13,
            -0.55
          ],
          "metadata": {
            "size": [
              0.45,
              0.45
            ]
          }
        },
        {
          "id": "red_cube",
          "type": "object",
          "label": "red_cube",
          "position": [
            -0.55,
            0.18,
            0.2
          ],
          "metadata": {
            "position": [
              -0.55,
              0.18,
              0.2
            ],
            "size": 0.2
          }
        },
        {
          "id": "blue_cube",
          "type": "object",
          "label": "blue_cube",
          "position": [
            0.45,
            0.18,
            -0.25
          ],
          "metadata": {
            "position": [
              0.45,
              0.18,
              -0.25
            ],
            "size": 0.2
          }
        },
        {
          "id": "glass_cup",
          "type": "object",
          "label": "glass_cup",
          "position": [
            0.05,
            0.2,
            0.55
          ],
          "metadata": {
            "position": [
              0.05,
              0.2,
              0.55
            ],
            "radius": 0.09,
            "height": 0.28
          }
        },
        {
          "id": "indicator:safe",
          "type": "indicator",
          "label": "safe",
          "metadata": {
            "value": "safe_zone"
          }
        },
        {
          "id": "indicator:unsafe",
          "type": "indicator",
          "label": "unsafe",
          "metadata": {
            "value": "restricted_zone"
          }
        }
      ],
      "edges": [
        {
          "from": "workspace",
          "to": "device",
          "relation": "contains"
        },
        {
          "from": "workspace",
          "to": "safe_zone",
          "relation": "contains"
        },
        {
          "from": "device",
          "to": "safe_zone",
          "relation": "targets"
        },
        {
          "from": "workspace",
          "to": "inspection_zone",
          "relation": "contains"
        },
        {
          "from": "device",
          "to": "inspection_zone",
          "relation": "targets"
        },
        {
          "from": "workspace",
          "to": "restricted_zone",
          "relation": "contains"
        },
        {
          "from": "device",
          "to": "restricted_zone",
          "relation": "targets"
        },
        {
          "from": "workspace",
          "to": "unsafe_zone",
          "relation": "contains"
        },
        {
          "from": "device",
          "to": "unsafe_zone",
          "relation": "targets"
        },
        {
          "from": "workspace",
          "to": "red_cube",
          "relation": "contains"
        },
        {
          "from": "device",
          "to": "red_cube",
          "relation": "targets"
        },
        {
          "from": "workspace",
          "to": "blue_cube",
          "relation": "contains"
        },
        {
          "from": "device",
          "to": "blue_cube",
          "relation": "targets"
        },
        {
          "from": "workspace",
          "to": "glass_cup",
          "relation": "contains"
        },
        {
          "from": "device",
          "to": "glass_cup",
          "relation": "targets"
        },
        {
          "from": "device",
          "to": "indicator:safe",
          "relation": "monitors"
        },
        {
          "from": "device",
          "to": "indicator:unsafe",
          "relation": "monitors"
        }
      ]
    },
    "normalized_capabilities": [
      {
        "raw": "read_register",
        "normalized": "automation.read_register",
        "capability_class": "automation",
        "device_types": [
          "plc_cabinet"
        ],
        "requires_target": true,
        "requires_value": false,
        "risk_hint": "low"
      },
      {
        "raw": "write_register",
        "normalized": "automation.write_register",
        "capability_class": "automation",
        "device_types": [
          "plc_cabinet"
        ],
        "requires_target": true,
        "requires_value": true,
        "risk_hint": "medium"
      },
      {
        "raw": "start_sequence",
        "normalized": "automation.start_sequence",
        "capability_class": "automation",
        "device_types": [
          "plc_cabinet"
        ],
        "requires_target": false,
        "requires_value": false,
        "risk_hint": "medium"
      },
      {
        "raw": "stop_sequence",
        "normalized": "automation.stop_sequence",
        "capability_class": "automation",
        "device_types": [
          "plc_cabinet"
        ],
        "requires_target": false,
        "requires_value": false,
        "risk_hint": "low"
      }
    ],
    "safety_profile": {
      "profile_version": "safety-profile.v1",
      "risk_class": "medium",
      "forbidden_zones": [
        "restricted_zone",
        "unsafe_zone"
      ],
      "workspace": {
        "x_min": -1.8,
        "x_max": 1.8,
        "y_min": 0,
        "z_min": -1.4,
        "z_max": 1.4,
        "y_max": 1.8
      },
      "max_speed": "normal",
      "force_limit": "medium",
      "policies": {
        "allow_throwing": false,
        "allow_high_force": false,
        "allow_outside_workspace": false,
        "require_logging": true,
        "require_human_confirmation_for_risky_actions": true
      }
    },
    "runtime_permissions": [
      {
        "permission": "simulation.run",
        "allowed": false,
        "scope": "plc_cabinet"
      },
      {
        "permission": "audit.export",
        "allowed": true,
        "scope": "plc_cabinet"
      },
      {
        "permission": "real_device.connect",
        "allowed": false,
        "scope": "plc_cabinet"
      },
      {
        "permission": "real_device.execute",
        "allowed": false,
        "scope": "plc_cabinet"
      }
    ],
    "adapter_binding": {
      "binding_version": "adapter-binding.v1",
      "adapter_id": "simulator-generic-plc-cabinet",
      "adapter_type": "simulator",
      "interface": "AdapterInterface",
      "transport": "virtual-device-runtime",
      "supported_commands": [
        "read_register",
        "write_register",
        "start_sequence",
        "stop_sequence"
      ],
      "real_device_enabled": false
    },
    "source_asset": {
      "license": "project-owned-generic",
      "brand": "generic",
      "source": "created-for-open-reality-studio",
      "allowed_use": [
        "simulation",
        "development",
        "testing"
      ]
    }
  },
  {
    "protocol_version": "openreality.protocol.v0.1",
    "asset_id": "generic-ptz-camera",
    "device_type": "camera_sensor",
    "manifest": {
      "protocol_version": "openreality.protocol.v0.1",
      "manifest_version": "device-manifest.v1",
      "asset_id": "generic-ptz-camera",
      "profile_id": "generic-ptz-camera",
      "device_id": "asset-generic-ptz-camera",
      "device_type": "camera_sensor",
      "display_name": "Generic PTZ Camera",
      "manufacturer": "RealityWarden",
      "model": "Generic PTZ Camera",
      "category": "vision",
      "simulator_fidelity": "semantic",
      "risk_class": "low",
      "supported_adapters": [
        "simulator"
      ],
      "public_alpha_runnable": true
    },
    "component_graph": {
      "graph_version": "component-graph.v1",
      "device_type": "camera_sensor",
      "nodes": [
        {
          "id": "device",
          "type": "device",
          "label": "camera_sensor",
          "position": [
            0,
            0,
            0
          ]
        },
        {
          "id": "workspace",
          "type": "workspace",
          "label": "workspace",
          "metadata": {
            "x_min": -2,
            "x_max": 2,
            "y_min": 0,
            "y_max": 2,
            "z_min": -2,
            "z_max": 2
          }
        },
        {
          "id": "camera_view",
          "type": "zone",
          "label": "camera_view",
          "position": [
            0,
            0.04,
            0
          ],
          "metadata": {
            "size": [
              1.2,
              0.8
            ]
          }
        },
        {
          "id": "privacy_zone",
          "type": "zone",
          "label": "privacy_zone",
          "position": [
            0.75,
            0.04,
            0.45
          ],
          "metadata": {
            "size": [
              0.55,
              0.45
            ]
          }
        },
        {
          "id": "red_cube",
          "type": "object",
          "label": "red_cube",
          "position": [
            -0.55,
            0.1,
            0
          ],
          "metadata": {
            "position": [
              -0.55,
              0.1,
              0
            ],
            "size": 0.15
          }
        },
        {
          "id": "blue_cube",
          "type": "object",
          "label": "blue_cube",
          "position": [
            0.55,
            0.1,
            0
          ],
          "metadata": {
            "position": [
              0.55,
              0.1,
              0
            ],
            "size": 0.15
          }
        },
        {
          "id": "glass_cup",
          "type": "object",
          "label": "glass_cup",
          "position": [
            0,
            0.1,
            0.45
          ],
          "metadata": {
            "position": [
              0,
              0.1,
              0.45
            ],
            "radius": 0.05,
            "height": 0.15
          }
        }
      ],
      "edges": [
        {
          "from": "workspace",
          "to": "device",
          "relation": "contains"
        },
        {
          "from": "workspace",
          "to": "camera_view",
          "relation": "contains"
        },
        {
          "from": "device",
          "to": "camera_view",
          "relation": "targets"
        },
        {
          "from": "workspace",
          "to": "privacy_zone",
          "relation": "contains"
        },
        {
          "from": "device",
          "to": "privacy_zone",
          "relation": "targets"
        },
        {
          "from": "workspace",
          "to": "red_cube",
          "relation": "contains"
        },
        {
          "from": "device",
          "to": "red_cube",
          "relation": "targets"
        },
        {
          "from": "workspace",
          "to": "blue_cube",
          "relation": "contains"
        },
        {
          "from": "device",
          "to": "blue_cube",
          "relation": "targets"
        },
        {
          "from": "workspace",
          "to": "glass_cup",
          "relation": "contains"
        },
        {
          "from": "device",
          "to": "glass_cup",
          "relation": "targets"
        }
      ]
    },
    "normalized_capabilities": [
      {
        "raw": "capture_frame",
        "normalized": "vision.capture_frame",
        "capability_class": "vision",
        "device_types": [
          "camera_sensor"
        ],
        "requires_target": false,
        "requires_value": false,
        "risk_hint": "low"
      },
      {
        "raw": "read_sensor",
        "normalized": "sensor.read_sensor",
        "capability_class": "sensor",
        "device_types": [
          "camera_sensor",
          "sensor_box"
        ],
        "requires_target": false,
        "requires_value": false,
        "risk_hint": "low"
      },
      {
        "raw": "scan_area",
        "normalized": "vision.scan_area",
        "capability_class": "vision",
        "device_types": [
          "robot_arm",
          "camera_sensor"
        ],
        "requires_target": false,
        "requires_value": false,
        "risk_hint": "low"
      }
    ],
    "safety_profile": {
      "profile_version": "safety-profile.v1",
      "risk_class": "low",
      "forbidden_zones": [
        "privacy_zone"
      ],
      "workspace": {
        "x_min": -2,
        "x_max": 2,
        "y_min": 0,
        "z_min": -2,
        "z_max": 2,
        "y_max": 2
      },
      "max_speed": "normal",
      "force_limit": "low",
      "policies": {
        "allow_throwing": false,
        "allow_high_force": false,
        "allow_outside_workspace": false,
        "require_logging": true,
        "require_human_confirmation_for_risky_actions": false
      }
    },
    "runtime_permissions": [
      {
        "permission": "simulation.run",
        "allowed": true,
        "scope": "camera_sensor"
      },
      {
        "permission": "audit.export",
        "allowed": true,
        "scope": "camera_sensor"
      },
      {
        "permission": "real_device.connect",
        "allowed": false,
        "scope": "camera_sensor"
      },
      {
        "permission": "real_device.execute",
        "allowed": false,
        "scope": "camera_sensor"
      }
    ],
    "adapter_binding": {
      "binding_version": "adapter-binding.v1",
      "adapter_id": "simulator-generic-ptz-camera",
      "adapter_type": "simulator",
      "interface": "AdapterInterface",
      "transport": "virtual-device-runtime",
      "supported_commands": [
        "capture_frame",
        "read_sensor",
        "scan_area"
      ],
      "real_device_enabled": false
    },
    "source_asset": {
      "license": "project-owned-generic",
      "brand": "generic",
      "source": "created-for-open-reality-studio",
      "allowed_use": [
        "simulation",
        "development",
        "testing"
      ]
    }
  },
  {
    "protocol_version": "openreality.protocol.v0.1",
    "asset_id": "generic-sensor-box",
    "device_type": "sensor_box",
    "manifest": {
      "protocol_version": "openreality.protocol.v0.1",
      "manifest_version": "device-manifest.v1",
      "asset_id": "generic-sensor-box",
      "profile_id": "generic-sensor-box",
      "device_id": "asset-generic-sensor-box",
      "device_type": "sensor_box",
      "display_name": "Generic Sensor Box",
      "manufacturer": "RealityWarden",
      "model": "Generic Sensor Box",
      "category": "sensors",
      "simulator_fidelity": "semantic",
      "risk_class": "low",
      "supported_adapters": [
        "simulator"
      ],
      "public_alpha_runnable": false
    },
    "component_graph": {
      "graph_version": "component-graph.v1",
      "device_type": "sensor_box",
      "nodes": [
        {
          "id": "device",
          "type": "device",
          "label": "sensor_box",
          "position": [
            0,
            0,
            0
          ]
        },
        {
          "id": "workspace",
          "type": "workspace",
          "label": "workspace",
          "metadata": {
            "x_min": -1.8,
            "x_max": 1.8,
            "y_min": 0,
            "z_min": -1.4,
            "z_max": 1.4,
            "y_max": 1.8
          }
        },
        {
          "id": "safe_zone",
          "type": "zone",
          "label": "safe_zone",
          "position": [
            0.75,
            0.13,
            0.2
          ],
          "metadata": {
            "size": [
              0.55,
              0.55
            ]
          }
        },
        {
          "id": "inspection_zone",
          "type": "zone",
          "label": "inspection_zone",
          "position": [
            -0.55,
            0.13,
            0.2
          ],
          "metadata": {
            "size": [
              0.55,
              0.55
            ]
          }
        },
        {
          "id": "restricted_zone",
          "type": "zone",
          "label": "restricted_zone",
          "position": [
            0.05,
            0.13,
            0.55
          ],
          "metadata": {
            "size": [
              0.45,
              0.45
            ]
          }
        },
        {
          "id": "unsafe_zone",
          "type": "zone",
          "label": "unsafe_zone",
          "position": [
            -0.9,
            0.13,
            -0.55
          ],
          "metadata": {
            "size": [
              0.45,
              0.45
            ]
          }
        },
        {
          "id": "red_cube",
          "type": "object",
          "label": "red_cube",
          "position": [
            -0.55,
            0.18,
            0.2
          ],
          "metadata": {
            "position": [
              -0.55,
              0.18,
              0.2
            ],
            "size": 0.2
          }
        },
        {
          "id": "blue_cube",
          "type": "object",
          "label": "blue_cube",
          "position": [
            0.45,
            0.18,
            -0.25
          ],
          "metadata": {
            "position": [
              0.45,
              0.18,
              -0.25
            ],
            "size": 0.2
          }
        },
        {
          "id": "glass_cup",
          "type": "object",
          "label": "glass_cup",
          "position": [
            0.05,
            0.2,
            0.55
          ],
          "metadata": {
            "position": [
              0.05,
              0.2,
              0.55
            ],
            "radius": 0.09,
            "height": 0.28
          }
        },
        {
          "id": "indicator:safe",
          "type": "indicator",
          "label": "safe",
          "metadata": {
            "value": "safe_zone"
          }
        },
        {
          "id": "indicator:unsafe",
          "type": "indicator",
          "label": "unsafe",
          "metadata": {
            "value": "restricted_zone"
          }
        }
      ],
      "edges": [
        {
          "from": "workspace",
          "to": "device",
          "relation": "contains"
        },
        {
          "from": "workspace",
          "to": "safe_zone",
          "relation": "contains"
        },
        {
          "from": "device",
          "to": "safe_zone",
          "relation": "targets"
        },
        {
          "from": "workspace",
          "to": "inspection_zone",
          "relation": "contains"
        },
        {
          "from": "device",
          "to": "inspection_zone",
          "relation": "targets"
        },
        {
          "from": "workspace",
          "to": "restricted_zone",
          "relation": "contains"
        },
        {
          "from": "device",
          "to": "restricted_zone",
          "relation": "targets"
        },
        {
          "from": "workspace",
          "to": "unsafe_zone",
          "relation": "contains"
        },
        {
          "from": "device",
          "to": "unsafe_zone",
          "relation": "targets"
        },
        {
          "from": "workspace",
          "to": "red_cube",
          "relation": "contains"
        },
        {
          "from": "device",
          "to": "red_cube",
          "relation": "targets"
        },
        {
          "from": "workspace",
          "to": "blue_cube",
          "relation": "contains"
        },
        {
          "from": "device",
          "to": "blue_cube",
          "relation": "targets"
        },
        {
          "from": "workspace",
          "to": "glass_cup",
          "relation": "contains"
        },
        {
          "from": "device",
          "to": "glass_cup",
          "relation": "targets"
        },
        {
          "from": "device",
          "to": "indicator:safe",
          "relation": "monitors"
        },
        {
          "from": "device",
          "to": "indicator:unsafe",
          "relation": "monitors"
        }
      ]
    },
    "normalized_capabilities": [
      {
        "raw": "read_sensor",
        "normalized": "sensor.read_sensor",
        "capability_class": "sensor",
        "device_types": [
          "camera_sensor",
          "sensor_box"
        ],
        "requires_target": false,
        "requires_value": false,
        "risk_hint": "low"
      },
      {
        "raw": "calibrate_sensor",
        "normalized": "sensor.calibrate_sensor",
        "capability_class": "sensor",
        "device_types": [
          "sensor_box"
        ],
        "requires_target": false,
        "requires_value": false,
        "risk_hint": "medium"
      },
      {
        "raw": "reset_sensor",
        "normalized": "sensor.reset_sensor",
        "capability_class": "sensor",
        "device_types": [
          "sensor_box"
        ],
        "requires_target": false,
        "requires_value": false,
        "risk_hint": "low"
      }
    ],
    "safety_profile": {
      "profile_version": "safety-profile.v1",
      "risk_class": "low",
      "forbidden_zones": [
        "restricted_zone",
        "unsafe_zone"
      ],
      "workspace": {
        "x_min": -1.8,
        "x_max": 1.8,
        "y_min": 0,
        "z_min": -1.4,
        "z_max": 1.4,
        "y_max": 1.8
      },
      "max_speed": "normal",
      "force_limit": "low",
      "policies": {
        "allow_throwing": false,
        "allow_high_force": false,
        "allow_outside_workspace": false,
        "require_logging": true,
        "require_human_confirmation_for_risky_actions": false
      }
    },
    "runtime_permissions": [
      {
        "permission": "simulation.run",
        "allowed": false,
        "scope": "sensor_box"
      },
      {
        "permission": "audit.export",
        "allowed": true,
        "scope": "sensor_box"
      },
      {
        "permission": "real_device.connect",
        "allowed": false,
        "scope": "sensor_box"
      },
      {
        "permission": "real_device.execute",
        "allowed": false,
        "scope": "sensor_box"
      }
    ],
    "adapter_binding": {
      "binding_version": "adapter-binding.v1",
      "adapter_id": "simulator-generic-sensor-box",
      "adapter_type": "simulator",
      "interface": "AdapterInterface",
      "transport": "virtual-device-runtime",
      "supported_commands": [
        "read_sensor",
        "calibrate_sensor",
        "reset_sensor"
      ],
      "real_device_enabled": false
    },
    "source_asset": {
      "license": "project-owned-generic",
      "brand": "generic",
      "source": "created-for-open-reality-studio",
      "allowed_use": [
        "simulation",
        "development",
        "testing"
      ]
    }
  },
  {
    "protocol_version": "openreality.protocol.v0.1",
    "asset_id": "generic-smart-light-panel",
    "device_type": "smart_light",
    "manifest": {
      "protocol_version": "openreality.protocol.v0.1",
      "manifest_version": "device-manifest.v1",
      "asset_id": "generic-smart-light-panel",
      "profile_id": "generic-smart-light-panel",
      "device_id": "asset-generic-smart-light-panel",
      "device_type": "smart_light",
      "display_name": "Generic Smart Light Panel",
      "manufacturer": "RealityWarden",
      "model": "Generic Smart Light Panel",
      "category": "building-automation",
      "simulator_fidelity": "semantic",
      "risk_class": "low",
      "supported_adapters": [
        "simulator"
      ],
      "public_alpha_runnable": true
    },
    "component_graph": {
      "graph_version": "component-graph.v1",
      "device_type": "smart_light",
      "nodes": [
        {
          "id": "device",
          "type": "device",
          "label": "smart_light",
          "position": [
            0,
            0,
            0
          ]
        },
        {
          "id": "workspace",
          "type": "workspace",
          "label": "workspace",
          "metadata": {
            "x_min": 0,
            "x_max": 1,
            "y_min": 0,
            "y_max": 1,
            "z_min": 0,
            "z_max": 1
          }
        },
        {
          "id": "office",
          "type": "zone",
          "label": "office",
          "position": [
            0,
            0.04,
            0
          ],
          "metadata": {
            "size": [
              1.4,
              1
            ]
          }
        },
        {
          "id": "operator_station",
          "type": "zone",
          "label": "operator_station",
          "position": [
            0.7,
            0.04,
            0.45
          ],
          "metadata": {
            "size": [
              0.5,
              0.4
            ]
          }
        },
        {
          "id": "red_cube",
          "type": "object",
          "label": "red_cube",
          "position": [
            -0.4,
            0.1,
            0
          ],
          "metadata": {
            "position": [
              -0.4,
              0.1,
              0
            ],
            "size": 0.15
          }
        },
        {
          "id": "blue_cube",
          "type": "object",
          "label": "blue_cube",
          "position": [
            0.4,
            0.1,
            0
          ],
          "metadata": {
            "position": [
              0.4,
              0.1,
              0
            ],
            "size": 0.15
          }
        },
        {
          "id": "glass_cup",
          "type": "object",
          "label": "glass_cup",
          "position": [
            0,
            0.1,
            0.5
          ],
          "metadata": {
            "position": [
              0,
              0.1,
              0.5
            ],
            "radius": 0.05,
            "height": 0.15
          }
        }
      ],
      "edges": [
        {
          "from": "workspace",
          "to": "device",
          "relation": "contains"
        },
        {
          "from": "workspace",
          "to": "office",
          "relation": "contains"
        },
        {
          "from": "device",
          "to": "office",
          "relation": "targets"
        },
        {
          "from": "workspace",
          "to": "operator_station",
          "relation": "contains"
        },
        {
          "from": "device",
          "to": "operator_station",
          "relation": "targets"
        },
        {
          "from": "workspace",
          "to": "red_cube",
          "relation": "contains"
        },
        {
          "from": "device",
          "to": "red_cube",
          "relation": "targets"
        },
        {
          "from": "workspace",
          "to": "blue_cube",
          "relation": "contains"
        },
        {
          "from": "device",
          "to": "blue_cube",
          "relation": "targets"
        },
        {
          "from": "workspace",
          "to": "glass_cup",
          "relation": "contains"
        },
        {
          "from": "device",
          "to": "glass_cup",
          "relation": "targets"
        }
      ]
    },
    "normalized_capabilities": [
      {
        "raw": "set_light",
        "normalized": "lighting.set_power",
        "capability_class": "lighting",
        "device_types": [
          "smart_light"
        ],
        "requires_target": false,
        "requires_value": true,
        "risk_hint": "low"
      },
      {
        "raw": "set_brightness",
        "normalized": "lighting.set_brightness",
        "capability_class": "lighting",
        "device_types": [
          "smart_light"
        ],
        "requires_target": false,
        "requires_value": true,
        "risk_hint": "low"
      },
      {
        "raw": "set_color",
        "normalized": "lighting.set_color",
        "capability_class": "lighting",
        "device_types": [
          "smart_light"
        ],
        "requires_target": false,
        "requires_value": true,
        "risk_hint": "low"
      }
    ],
    "safety_profile": {
      "profile_version": "safety-profile.v1",
      "risk_class": "low",
      "forbidden_zones": [],
      "workspace": {
        "x_min": 0,
        "x_max": 1,
        "y_min": 0,
        "z_min": 0,
        "z_max": 1,
        "y_max": 1
      },
      "max_speed": "normal",
      "force_limit": "low",
      "policies": {
        "allow_throwing": false,
        "allow_high_force": false,
        "allow_outside_workspace": false,
        "require_logging": true,
        "require_human_confirmation_for_risky_actions": false
      }
    },
    "runtime_permissions": [
      {
        "permission": "simulation.run",
        "allowed": true,
        "scope": "smart_light"
      },
      {
        "permission": "audit.export",
        "allowed": true,
        "scope": "smart_light"
      },
      {
        "permission": "real_device.connect",
        "allowed": false,
        "scope": "smart_light"
      },
      {
        "permission": "real_device.execute",
        "allowed": false,
        "scope": "smart_light"
      }
    ],
    "adapter_binding": {
      "binding_version": "adapter-binding.v1",
      "adapter_id": "simulator-generic-smart-light-panel",
      "adapter_type": "simulator",
      "interface": "AdapterInterface",
      "transport": "virtual-device-runtime",
      "supported_commands": [
        "set_light",
        "set_brightness",
        "set_color"
      ],
      "real_device_enabled": false
    },
    "source_asset": {
      "license": "project-owned-generic",
      "brand": "generic",
      "source": "created-for-open-reality-studio",
      "allowed_use": [
        "simulation",
        "development",
        "testing"
      ]
    }
  },
  {
    "protocol_version": "openreality.protocol.v0.1",
    "asset_id": "generic-warehouse-rack",
    "device_type": "warehouse_rack",
    "manifest": {
      "protocol_version": "openreality.protocol.v0.1",
      "manifest_version": "device-manifest.v1",
      "asset_id": "generic-warehouse-rack",
      "profile_id": "generic-warehouse-rack",
      "device_id": "asset-generic-warehouse-rack",
      "device_type": "warehouse_rack",
      "display_name": "Generic Warehouse Rack",
      "manufacturer": "RealityWarden",
      "model": "Generic Warehouse Rack",
      "category": "warehouse",
      "simulator_fidelity": "semantic",
      "risk_class": "low",
      "supported_adapters": [
        "simulator"
      ],
      "public_alpha_runnable": false
    },
    "component_graph": {
      "graph_version": "component-graph.v1",
      "device_type": "warehouse_rack",
      "nodes": [
        {
          "id": "device",
          "type": "device",
          "label": "warehouse_rack",
          "position": [
            0,
            0,
            0
          ]
        },
        {
          "id": "workspace",
          "type": "workspace",
          "label": "workspace",
          "metadata": {
            "x_min": -1.8,
            "x_max": 1.8,
            "y_min": 0,
            "z_min": -1.4,
            "z_max": 1.4,
            "y_max": 1.8
          }
        },
        {
          "id": "safe_zone",
          "type": "zone",
          "label": "safe_zone",
          "position": [
            0.75,
            0.13,
            0.2
          ],
          "metadata": {
            "size": [
              0.55,
              0.55
            ]
          }
        },
        {
          "id": "inspection_zone",
          "type": "zone",
          "label": "inspection_zone",
          "position": [
            -0.55,
            0.13,
            0.2
          ],
          "metadata": {
            "size": [
              0.55,
              0.55
            ]
          }
        },
        {
          "id": "restricted_zone",
          "type": "zone",
          "label": "restricted_zone",
          "position": [
            0.05,
            0.13,
            0.55
          ],
          "metadata": {
            "size": [
              0.45,
              0.45
            ]
          }
        },
        {
          "id": "unsafe_zone",
          "type": "zone",
          "label": "unsafe_zone",
          "position": [
            -0.9,
            0.13,
            -0.55
          ],
          "metadata": {
            "size": [
              0.45,
              0.45
            ]
          }
        },
        {
          "id": "red_cube",
          "type": "object",
          "label": "red_cube",
          "position": [
            -0.55,
            0.18,
            0.2
          ],
          "metadata": {
            "position": [
              -0.55,
              0.18,
              0.2
            ],
            "size": 0.2
          }
        },
        {
          "id": "blue_cube",
          "type": "object",
          "label": "blue_cube",
          "position": [
            0.45,
            0.18,
            -0.25
          ],
          "metadata": {
            "position": [
              0.45,
              0.18,
              -0.25
            ],
            "size": 0.2
          }
        },
        {
          "id": "glass_cup",
          "type": "object",
          "label": "glass_cup",
          "position": [
            0.05,
            0.2,
            0.55
          ],
          "metadata": {
            "position": [
              0.05,
              0.2,
              0.55
            ],
            "radius": 0.09,
            "height": 0.28
          }
        },
        {
          "id": "indicator:safe",
          "type": "indicator",
          "label": "safe",
          "metadata": {
            "value": "safe_zone"
          }
        },
        {
          "id": "indicator:unsafe",
          "type": "indicator",
          "label": "unsafe",
          "metadata": {
            "value": "restricted_zone"
          }
        }
      ],
      "edges": [
        {
          "from": "workspace",
          "to": "device",
          "relation": "contains"
        },
        {
          "from": "workspace",
          "to": "safe_zone",
          "relation": "contains"
        },
        {
          "from": "device",
          "to": "safe_zone",
          "relation": "targets"
        },
        {
          "from": "workspace",
          "to": "inspection_zone",
          "relation": "contains"
        },
        {
          "from": "device",
          "to": "inspection_zone",
          "relation": "targets"
        },
        {
          "from": "workspace",
          "to": "restricted_zone",
          "relation": "contains"
        },
        {
          "from": "device",
          "to": "restricted_zone",
          "relation": "targets"
        },
        {
          "from": "workspace",
          "to": "unsafe_zone",
          "relation": "contains"
        },
        {
          "from": "device",
          "to": "unsafe_zone",
          "relation": "targets"
        },
        {
          "from": "workspace",
          "to": "red_cube",
          "relation": "contains"
        },
        {
          "from": "device",
          "to": "red_cube",
          "relation": "targets"
        },
        {
          "from": "workspace",
          "to": "blue_cube",
          "relation": "contains"
        },
        {
          "from": "device",
          "to": "blue_cube",
          "relation": "targets"
        },
        {
          "from": "workspace",
          "to": "glass_cup",
          "relation": "contains"
        },
        {
          "from": "device",
          "to": "glass_cup",
          "relation": "targets"
        },
        {
          "from": "device",
          "to": "indicator:safe",
          "relation": "monitors"
        },
        {
          "from": "device",
          "to": "indicator:unsafe",
          "relation": "monitors"
        }
      ]
    },
    "normalized_capabilities": [
      {
        "raw": "scan_slot",
        "normalized": "warehouse.scan_slot",
        "capability_class": "warehouse",
        "device_types": [
          "warehouse_rack"
        ],
        "requires_target": true,
        "requires_value": false,
        "risk_hint": "low"
      },
      {
        "raw": "reserve_slot",
        "normalized": "warehouse.reserve_slot",
        "capability_class": "warehouse",
        "device_types": [
          "warehouse_rack"
        ],
        "requires_target": true,
        "requires_value": false,
        "risk_hint": "low"
      },
      {
        "raw": "release_slot",
        "normalized": "warehouse.release_slot",
        "capability_class": "warehouse",
        "device_types": [
          "warehouse_rack"
        ],
        "requires_target": true,
        "requires_value": false,
        "risk_hint": "low"
      },
      {
        "raw": "mark_item",
        "normalized": "warehouse.mark_item",
        "capability_class": "warehouse",
        "device_types": [
          "warehouse_rack"
        ],
        "requires_target": true,
        "requires_value": true,
        "risk_hint": "low"
      }
    ],
    "safety_profile": {
      "profile_version": "safety-profile.v1",
      "risk_class": "low",
      "forbidden_zones": [
        "restricted_zone",
        "unsafe_zone"
      ],
      "workspace": {
        "x_min": -1.8,
        "x_max": 1.8,
        "y_min": 0,
        "z_min": -1.4,
        "z_max": 1.4,
        "y_max": 1.8
      },
      "max_speed": "normal",
      "force_limit": "low",
      "policies": {
        "allow_throwing": false,
        "allow_high_force": false,
        "allow_outside_workspace": false,
        "require_logging": true,
        "require_human_confirmation_for_risky_actions": false
      }
    },
    "runtime_permissions": [
      {
        "permission": "simulation.run",
        "allowed": false,
        "scope": "warehouse_rack"
      },
      {
        "permission": "audit.export",
        "allowed": true,
        "scope": "warehouse_rack"
      },
      {
        "permission": "real_device.connect",
        "allowed": false,
        "scope": "warehouse_rack"
      },
      {
        "permission": "real_device.execute",
        "allowed": false,
        "scope": "warehouse_rack"
      }
    ],
    "adapter_binding": {
      "binding_version": "adapter-binding.v1",
      "adapter_id": "simulator-generic-warehouse-rack",
      "adapter_type": "simulator",
      "interface": "AdapterInterface",
      "transport": "virtual-device-runtime",
      "supported_commands": [
        "scan_slot",
        "reserve_slot",
        "release_slot",
        "mark_item"
      ],
      "real_device_enabled": false
    },
    "source_asset": {
      "license": "project-owned-generic",
      "brand": "generic",
      "source": "created-for-open-reality-studio",
      "allowed_use": [
        "simulation",
        "development",
        "testing"
      ]
    }
  }
]
